{
"meta":{"test_sets":[],"test_metrics":[],"learn_metrics":[{"best_value":"Min","name":"RMSE"}],"launch_mode":"Train","parameters":"","iteration_count":100,"learn_sets":["learn"],"name":"experiment"},
"iterations":[
{"learn":[13.99348315],"iteration":0,"passed_time":0.0008835178515,"remaining_time":0.0874682673},
{"learn":[13.08679896],"iteration":1,"passed_time":0.001575043637,"remaining_time":0.07717713823},
{"learn":[12.24911066],"iteration":2,"passed_time":0.002222585313,"remaining_time":0.07186359178},
{"learn":[11.53058054],"iteration":3,"passed_time":0.002887520461,"remaining_time":0.06930049107},
{"learn":[10.84207334],"iteration":4,"passed_time":0.003559854995,"remaining_time":0.06763724491},
{"learn":[10.30180643],"iteration":5,"passed_time":0.004232089733,"remaining_time":0.06630273915},
{"learn":[9.78256195],"iteration":6,"passed_time":0.004910478573,"remaining_time":0.06523921532},
{"learn":[9.383051568],"iteration":7,"passed_time":0.005600151619,"remaining_time":0.06440174362},
{"learn":[8.99755936],"iteration":8,"passed_time":0.006262118914,"remaining_time":0.06331698014},
{"learn":[8.583469865],"iteration":9,"passed_time":0.006897372635,"remaining_time":0.06207635371},
{"learn":[8.227667947],"iteration":10,"passed_time":0.007537433931,"remaining_time":0.06098469272},
{"learn":[7.929112785],"iteration":11,"passed_time":0.008171510345,"remaining_time":0.0599244092},
{"learn":[7.684630471],"iteration":12,"passed_time":0.008800972991,"remaining_time":0.05889881925},
{"learn":[7.424891669],"iteration":13,"passed_time":0.009448268792,"remaining_time":0.05803936543},
{"learn":[7.201854992],"iteration":14,"passed_time":0.01006055347,"remaining_time":0.05700980297},
{"learn":[6.982008334],"iteration":15,"passed_time":0.01072988254,"remaining_time":0.05633188335},
{"learn":[6.825014781],"iteration":16,"passed_time":0.01140553205,"remaining_time":0.05568583294},
{"learn":[6.660105229],"iteration":17,"passed_time":0.01220766606,"remaining_time":0.05561270094},
{"learn":[6.506800805],"iteration":18,"passed_time":0.01287538393,"remaining_time":0.05488979466},
{"learn":[6.376253871],"iteration":19,"passed_time":0.01351281726,"remaining_time":0.05405126905},
{"learn":[6.266699941],"iteration":20,"passed_time":0.01416935362,"remaining_time":0.05330375884},
{"learn":[6.183713198],"iteration":21,"passed_time":0.01484455621,"remaining_time":0.05263069928},
{"learn":[6.095001646],"iteration":22,"passed_time":0.01548417927,"remaining_time":0.05183833929},
{"learn":[6.017210026],"iteration":23,"passed_time":0.01613825254,"remaining_time":0.05110446636},
{"learn":[5.926879154],"iteration":24,"passed_time":0.01677364655,"remaining_time":0.05032093965},
{"learn":[5.869115164],"iteration":25,"passed_time":0.0174325245,"remaining_time":0.04961564665},
{"learn":[5.794295297],"iteration":26,"passed_time":0.01806419713,"remaining_time":0.04884023667},
{"learn":[5.736659494],"iteration":27,"passed_time":0.01869733922,"remaining_time":0.04807887227},
{"learn":[5.688737334],"iteration":28,"passed_time":0.019373628,"remaining_time":0.04743198578},
{"learn":[5.646276694],"iteration":29,"passed_time":0.02000266398,"remaining_time":0.04667288261},
{"learn":[5.60024339],"iteration":30,"passed_time":0.02064406891,"remaining_time":0.04594970176},
{"learn":[5.562148648],"iteration":31,"passed_time":0.02114161249,"remaining_time":0.04492592653},
{"learn":[5.518152613],"iteration":32,"passed_time":0.02178185168,"remaining_time":0.04422375947},
{"learn":[5.469872589],"iteration":33,"passed_time":0.02241543634,"remaining_time":0.04351231761},
{"learn":[5.45057841],"iteration":34,"passed_time":0.0230777551,"remaining_time":0.04285868803},
{"learn":[5.428112506],"iteration":35,"passed_time":0.0237593027,"remaining_time":0.04223876036},
{"learn":[5.402930191],"iteration":36,"passed_time":0.02439495995,"remaining_time":0.04153736424},
{"learn":[5.378422269],"iteration":37,"passed_time":0.02503615082,"remaining_time":0.0408484566},
{"learn":[5.357370046],"iteration":38,"passed_time":0.02567924939,"remaining_time":0.04016497982},
{"learn":[5.323772692],"iteration":39,"passed_time":0.02635252982,"remaining_time":0.03952879474},
{"learn":[5.299500716],"iteration":40,"passed_time":0.02716813778,"remaining_time":0.0390956129},
{"learn":[5.281272066],"iteration":41,"passed_time":0.0279740814,"remaining_time":0.03863087432},
{"learn":[5.263540736],"iteration":42,"passed_time":0.028700115,"remaining_time":0.03804433848},
{"learn":[5.254240202],"iteration":43,"passed_time":0.02913076761,"remaining_time":0.03707552241},
{"learn":[5.239421602],"iteration":44,"passed_time":0.02979130739,"remaining_time":0.03641159792},
{"learn":[5.217876804],"iteration":45,"passed_time":0.03043406318,"remaining_time":0.03572694373},
{"learn":[5.196339687],"iteration":46,"passed_time":0.03110118083,"remaining_time":0.03507154434},
{"learn":[5.173762601],"iteration":47,"passed_time":0.03176585564,"remaining_time":0.03441301028},
{"learn":[5.157351931],"iteration":48,"passed_time":0.03243888875,"remaining_time":0.03376292502},
{"learn":[5.145163366],"iteration":49,"passed_time":0.03312368624,"remaining_time":0.03312368624},
{"learn":[5.132132849],"iteration":50,"passed_time":0.03378428821,"remaining_time":0.03245941416},
{"learn":[5.121703354],"iteration":51,"passed_time":0.03444523151,"remaining_time":0.03179559832},
{"learn":[5.117554392],"iteration":52,"passed_time":0.03498558768,"remaining_time":0.03102495511},
{"learn":[5.110919902],"iteration":53,"passed_time":0.03565718459,"remaining_time":0.03037463872},
{"learn":[5.099775896],"iteration":54,"passed_time":0.03630749452,"remaining_time":0.02970613188},
{"learn":[5.081971316],"iteration":55,"passed_time":0.03694145668,"remaining_time":0.02902543025},
{"learn":[5.063256046],"iteration":56,"passed_time":0.03760521741,"remaining_time":0.02836884822},
{"learn":[5.046093491],"iteration":57,"passed_time":0.03832145362,"remaining_time":0.02775001814},
{"learn":[5.032051633],"iteration":58,"passed_time":0.03896981536,"remaining_time":0.02708071915},
{"learn":[5.018495584],"iteration":59,"passed_time":0.03963671027,"remaining_time":0.02642447352},
{"learn":[5.008909962],"iteration":60,"passed_time":0.04027827141,"remaining_time":0.02575168172},
{"learn":[4.99771367],"iteration":61,"passed_time":0.04107579527,"remaining_time":0.02517548742},
{"learn":[4.989916869],"iteration":62,"passed_time":0.04179642106,"remaining_time":0.02454710443},
{"learn":[4.981820588],"iteration":63,"passed_time":0.04253701405,"remaining_time":0.02392707041},
{"learn":[4.960666189],"iteration":64,"passed_time":0.04324919911,"remaining_time":0.02328803029},
{"learn":[4.94706364],"iteration":65,"passed_time":0.04398662828,"remaining_time":0.0226597782},
{"learn":[4.938906099],"iteration":66,"passed_time":0.04466499108,"remaining_time":0.02199917471},
{"learn":[4.920677053],"iteration":67,"passed_time":0.04535520794,"remaining_time":0.02134362727},
{"learn":[4.903676084],"iteration":68,"passed_time":0.0460315647,"remaining_time":0.02068084791},
{"learn":[4.897635401],"iteration":69,"passed_time":0.04672266671,"remaining_time":0.02002400002},
{"learn":[4.889952833],"iteration":70,"passed_time":0.04736787547,"remaining_time":0.01934744209},
{"learn":[4.882302534],"iteration":71,"passed_time":0.0480560617,"remaining_time":0.01868846844},
{"learn":[4.873750572],"iteration":72,"passed_time":0.0487334251,"remaining_time":0.01802469147},
{"learn":[4.865386403],"iteration":73,"passed_time":0.04940421351,"remaining_time":0.01735823718},
{"learn":[4.857493367],"iteration":74,"passed_time":0.05009997268,"remaining_time":0.01669999089},
{"learn":[4.848032763],"iteration":75,"passed_time":0.0507645665,"remaining_time":0.01603091574},
{"learn":[4.839634573],"iteration":76,"passed_time":0.05142835905,"remaining_time":0.01536171764},
{"learn":[4.826534384],"iteration":77,"passed_time":0.05210143989,"remaining_time":0.01469527792},
{"learn":[4.81907123],"iteration":78,"passed_time":0.05274510542,"remaining_time":0.01402085081},
{"learn":[4.811944485],"iteration":79,"passed_time":0.05340416272,"remaining_time":0.01335104068},
{"learn":[4.807339578],"iteration":80,"passed_time":0.05404764023,"remaining_time":0.01267784153},
{"learn":[4.79836765],"iteration":81,"passed_time":0.05486632812,"remaining_time":0.01204382812},
{"learn":[4.776924133],"iteration":82,"passed_time":0.05556925671,"remaining_time":0.01138165499},
{"learn":[4.768244651],"iteration":83,"passed_time":0.05623773246,"remaining_time":0.01071194904},
{"learn":[4.761240486],"iteration":84,"passed_time":0.05701807401,"remaining_time":0.01006201306},
{"learn":[4.751984925],"iteration":85,"passed_time":0.05768859196,"remaining_time":0.009391166134},
{"learn":[4.733949017],"iteration":86,"passed_time":0.05835549845,"remaining_time":0.008719787125},
{"learn":[4.727594275],"iteration":87,"passed_time":0.05905512653,"remaining_time":0.0080529718},
{"learn":[4.713457982],"iteration":88,"passed_time":0.05974696762,"remaining_time":0.007384456672},
{"learn":[4.706779065],"iteration":89,"passed_time":0.0604345406,"remaining_time":0.006714948956},
{"learn":[4.696353448],"iteration":90,"passed_time":0.06110581643,"remaining_time":0.006043432394},
{"learn":[4.685069481],"iteration":91,"passed_time":0.0617573138,"remaining_time":0.0053702012},
{"learn":[4.679105072],"iteration":92,"passed_time":0.06241800978,"remaining_time":0.004698129768},
{"learn":[4.669998076],"iteration":93,"passed_time":0.06308390239,"remaining_time":0.004026632067},
{"learn":[4.655194439],"iteration":94,"passed_time":0.06375090433,"remaining_time":0.003355310754},
{"learn":[4.6402433],"iteration":95,"passed_time":0.06441194598,"remaining_time":0.002683831083},
{"learn":[4.620675835],"iteration":96,"passed_time":0.0651060361,"remaining_time":0.002013588745},
{"learn":[4.617949274],"iteration":97,"passed_time":0.06577229029,"remaining_time":0.001342291639},
{"learn":[4.611545659],"iteration":98,"passed_time":0.06646015399,"remaining_time":0.0006713146868},
{"learn":[4.59686047],"iteration":99,"passed_time":0.06710893516,"remaining_time":0}
]}